jxb_mobilenetv3/__init__.py
jxb_mobilenetv3/config/__init__.py
jxb_mobilenetv3/config/config.yaml
jxb_mobilenetv3/src/__init__.py
jxb_mobilenetv3/src/dataset.py
jxb_mobilenetv3/src/mobilenet_v3.py
jxb_mobilenetv3/src/predict.py
jxb_mobilenetv3/src/train.py
jxb_mobilenetv3/utils/__init__.py
jxb_mobilenetv3/utils/utils.py
jxb_mobilenetv3-1.0.0.dist-info/METADATA
jxb_mobilenetv3-1.0.0.dist-info/WHEEL
jxb_mobilenetv3-1.0.0.dist-info/top_level.txt
jxb_mobilenetv3-1.0.0.dist-info/RECORD
