Metadata-Version: 2.1
Name: jxb-mobilenetv3
Version: 1.0.0
Summary: A MobileNetV3-based classifier
Home-page: https://github.com/Starsjxb6/jxb-mobilenetv3
Author: Xiaobo Jia
Author-email: 1428340048@qq.com
License: MIT
Platform: UNKNOWN
Classifier: License :: OSI Approved :: MIT License
Classifier: Programming Language :: Python :: 3
Classifier: Operating System :: OS Independent
Requires-Python: >=3.6
Requires-Dist: matplotlib (==3.7.5)
Requires-Dist: numpy (==1.23.5)
Requires-Dist: opencv-python (==4.10.0.84)
Requires-Dist: pillow (==10.4.0)
Requires-Dist: pyyaml (==6.0)
Requires-Dist: scikit-learn (==1.3.2)
Requires-Dist: seaborn (==0.13.2)
Requires-Dist: torch (==2.1.0)
Requires-Dist: torchvision (==0.16.0)
Requires-Dist: tqdm (==4.66.5)
